{
  "frame_index": 6,
  "local_intent": "Verify stable grasp, raise the held green_bottle by 0.10 m, then confirm it remains held.",
  "plugs_into": { "path_from_root": ["MainTree"], "mode": "replace-only" },
  "bb_read": [],
  "bb_write": [],
  "assumptions": ["Gripper is already holding the green_bottle after a successful grasp."],
  "coherence_with_global": "Implements the RaiseHeld step following IsGraspStable in GLOBAL_BT and confirms retention with ObjectInGripper before proceeding to place.",
  "format_checks": {
    "single_root_composite": true,
    "decorators_single_child": true,
    "only_known_nodes": true,
    "only_binned_values": true
  }
}