{
  "frame_index": 5,
  "local_intent": "Execute the opening of the hinged fridge door and verify it is open.",
  "plugs_into": { "path_from_root": ["MainTree"], "mode": "replace-only" },
  "bb_read": [],
  "bb_write": [],
  "assumptions": [
    "Handle is already grasped securely.",
    "Robot is positioned in front of the fridge."
  ],
  "coherence_with_global": "Matches the global plan: set yaw, align to handle, open the hinged door, wait briefly, then confirm ContainerOpen before proceeding.",
  "format_checks": {
    "single_root_composite": true,
    "decorators_single_child": true,
    "only_known_nodes": true,
    "only_binned_values": true
  }
}
