{
  "name": "pal_v1_symbolic_14",
  "version": "1.0",
  "description": "PAL v1 (Symbolic 14) for proposer dataset",
  "primitives": {
    "GRASP": {
      "params": {"obj": "string"},
      "required": ["obj"]
    },
    "PLACE_ON_TOP": {
      "params": {"obj": "string"},
      "required": ["obj"]
    },
    "PLACE_INSIDE": {
      "params": {"obj": "string"},
      "required": ["obj"]
    },
    "OPEN": {
      "params": {"obj": "string"},
      "required": ["obj"]
    },
    "CLOSE": {
      "params": {"obj": "string"},
      "required": ["obj"]
    },
    "NAVIGATE_TO": {
      "params": {"obj": "string"},
      "required": ["obj"]
    },
    "RELEASE": {
      "params": {},
      "required": []
    },
    "TOGGLE_ON": {
      "params": {"obj": "string"},
      "required": ["obj"]
    },
    "TOGGLE_OFF": {
      "params": {"obj": "string"},
      "required": ["obj"]
    },
    "SOAK_UNDER": {
      "params": {"obj": "string"},
      "required": ["obj"]
    },
    "SOAK_INSIDE": {
      "params": {"obj": "string"},
      "required": ["obj"]
    },
    "WIPE": {
      "params": {"obj": "string"},
      "required": ["obj"]
    },
    "CUT": {
      "params": {"obj": "string"},
      "required": ["obj"]
    },
    "PLACE_NEAR_HEATING_ELEMENT": {
      "params": {"obj": "string"},
      "required": ["obj"]
    }
  }
}
