{
  "frame_index": 5,
  "local_intent": "Execute grasp at computed pose, close gripper with set force, and verify stability.",
  "plugs_into": { "path_from_root": ["MainTree"], "mode": "replace-only" },
  "bb_read": ["goal_pose"],
  "bb_write": [],
  "assumptions": ["goal_pose has been computed and is reachable"],
  "coherence_with_global": "Aligns with grasp phase of GLOBAL_BT: uses computed goal_pose, performs GraspAtPose with pinch, closes gripper at force 20 (1500 ms), then verifies grasp stability.",
  "format_checks": {
    "single_root_composite": true,
    "decorators_single_child": true,
    "only_known_nodes": true,
    "only_binned_values": true
  }
}