{
  "frame_index": 5,
  "local_intent": "Transfer phase: push the T-block rightward after contact and yaw set, then verify the block is at the target outline.",
  "plugs_into": { "path_from_root": ["MainTree"], "mode": "replace-only" },
  "bb_read": [],
  "bb_write": [],
  "assumptions": [],
  "coherence_with_global": "Matches GLOBAL_BT transfer: perceive t_block → align and establish contact → set yaw 0 → Push distance 0.2 at direction 0 → verify with IsAt(target_T). Uses only library nodes and binned values for constrained ports.",
  "format_checks": {
    "single_root_composite": true,
    "decorators_single_child": true,
    "only_known_nodes": true,
    "only_binned_values": true
  }
}
