{
  "frame_index": 2,
  "local_intent": "Ensure the green_target is visible; if not, scan in a grid with retries.",
  "plugs_into": { "path_from_root": ["MainTree"], "mode": "replace-only" },
  "bb_read": [],
  "bb_write": [],
  "assumptions": ["Camera view unobstructed", "Scan movement safe for workspace"],
  "coherence_with_global": "Implements the second perception step in GLOBAL_BT: retry visibility of green_target with grid scanning and bounded timeout.",
  "format_checks": {
    "single_root_composite": true,
    "decorators_single_child": true,
    "only_known_nodes": true,
    "only_binned_values": true
  }
}