{
  "frame_index": 2,
  "local_intent": "Detect the white_plate (with retries), verify visibility, approach and align to 0.01 tolerance, let system settle, re-verify visibility before grasping.",
  "plugs_into": { "path_from_root": ["MainTree"], "mode": "replace-only" },
  "bb_read": [],
  "bb_write": [],
  "assumptions": [
    "Robot powered and homed",
    "Gripper open and empty",
    "Camera view unobstructed",
    "White plate is detectable from current viewpoint"
  ],
  "coherence_with_global": "Implements the 'approach' phase of the global BT: retries detection if needed, confirms visibility, performs ApproachAndAlign with the exact tolerance and timeout from the global tree, waits briefly to stabilize, and re-checks visibility before proceeding to ComputeGraspPose/Pick.",
  "format_checks": {
    "single_root_composite": true,
    "decorators_single_child": true,
    "only_known_nodes": true,
    "only_binned_values": true
  }
}