{
  "frame_index": 2,
  "local_intent": "Perceive the T-block and move the tool 3cm above it to begin the approach.",
  "plugs_into": { "path_from_root": ["MainTree"], "mode": "replace-only" },
  "bb_read": [],
  "bb_write": [],
  "assumptions": ["Camera view contains the block_T."],
  "coherence_with_global": "Matches the global approach phase by detecting block_T then executing MoveAbove with the same parameters, preparing for later align/push steps.",
  "format_checks": {
    "single_root_composite": true,
    "decorators_single_child": true,
    "only_known_nodes": true,
    "only_binned_values": true
  }
}
