{
  "frame_index": 3,
  "local_intent": "Adjust wrist orientation to 90 degrees yaw for proper bin lid grasping approach",
  "plugs_into": { "path_from_root": ["MainTree"], "mode": "replace-only" },
  "bb_read": [],
  "bb_write": [],
  "assumptions": [
    "End-effector is positioned near the lid edge and alignment is already achieved",
    "90° yaw prepares gripper jaws for a perpendicular grasp on lid edge"
  ],
  "coherence_with_global": "Matches the global sequence where SetTCPYaw=90 occurs after alignment and before opening the gripper. Preserves correct stepwise progression for the lid-opening task.",
  "format_checks": {
    "single_root_composite": true,
    "decorators_single_child": true,
    "only_known_nodes": true,
    "only_binned_values": true
  }
}
