{
  "dataset_id": "ucsd_pick_and_place_dataset_converted_externally_to_rlds_0.1.0",
  "episode_id": "episode_099",
  "task_summary": "The robot is instructed to place the pot in the sink. The BT performs object localization, approaches and grasps the pot, moves above the sink, and places the pot within it.",
  "task_long_description": {
    "overview": "This episode involves a robot interacting with a toy kitchen scene that features a pot on a stove and an empty sink. The robot must perceive and localize the pot, approach and pick it up using a top grasp, then transport and place it into the sink. It uses perception checks, alignment, and contact-based feedback throughout. No other objects are manipulated.",
    "preconditions": [
      "Pot is visible and on the stove/counter near sink",
      "Sink area is clear",
      "Robot gripper is empty and operational"
    ],
    "stepwise_plan": [
      "Scan for and detect the pot",
      "Approach pot from above and open gripper",
      "Compute top grasp pose and align for grasp",
      "Lower until contact and close gripper",
      "Verify grasp is stable",
      "Detect and move to sink",
      "Approach above sink and align",
      "Place pot onto sink surface",
      "Open gripper to release pot and retreat"
    ],
    "success_criteria": [
      "Pot is fully placed within the sink",
      "Pot is no longer in its original position",
      "No collisions or drops occur during transport"
    ],
    "failure_and_recovery": [
      "If the pot is not visible, retry scanning up to 3 times",
      "If grasp fails, repeat perception and approach",
      "If sink is not detected, repeat visual detection"
    ],
    "termination": "Episode ends once pot is placed in sink and robot has retreated"
  },
  "frame_ranking": {
    "order": ["frame_3","frame_5","frame_2","frame_6","frame_1","frame_4","frame_7","frame_0","frame_8"],
    "scores": {
      "frame_0": 0.12,
      "frame_1": 0.34,
      "frame_2": 0.56,
      "frame_3": 0.92,
      "frame_4": 0.28,
      "frame_5": 0.80,
      "frame_6": 0.49,
      "frame_7": 0.18,
      "frame_8": 0.05
    },
    "rationale_per_frame": {
      "frame_3": {
        "now_evidence": "first stable contact and alignment cue visible",
        "predicts_next": "push actuation expected; confirms goal direction",
        "uncertainty_reduction": "high"
      }
    }
  },
  "task_instruction": "place the pot in the sink",
  "instruction_to_ports": {
    "force": 10,
    "timeout_ms": 1000,
    "tolerance": 0.005,
    "retry_attempts": 3
  },
  "frame_source": "contact_sheet",
  "frame_order": ["frame_0","frame_1","frame_2","frame_3","frame_4","frame_5","frame_6","frame_7","frame_8"],
  "objects": ["pot", "sink", "stove", "counter"],
  "objects_from_instruction": ["pot", "sink"],
  "blackboard_keys": ["std_top"],
  "node_specs": [
    {
      "id": "IsObjectVisible",
      "type": "Condition",
      "ports": {"target":"pot"},
      "description": "Returns true if pot is visible to perception"
    },
    {
      "id": "ScanForTarget",
      "type": "Action",
      "ports": {"target":"pot","pattern":"raster","max_attempts":3,"timeout_ms":1000},
      "description": "Attempts to re-locate pot using raster scan"
    },
    {
      "id": "DetectObject",
      "type": "Action",
      "ports": {"target":"pot","timeout_ms":800},
      "description": "Detects and localizes the pot"
    },
    {
      "id": "OpenGripper",
      "type": "Action",
      "ports": {"width":0.08,"timeout_ms":500},
      "description": "Opens gripper to specified width"
    },
    {
      "id": "MoveAbove",
      "type": "Action",
      "ports": {"target":"pot","offset_z":0.05,"timeout_ms":1000},
      "description": "Moves gripper above the pot"
    },
    {
      "id": "ComputeGraspPose",
      "type": "Action",
      "ports": {"target":"pot","strategy":"top","result_key":"std_top"},
      "description": "Computes top grasp pose for the pot"
    },
    {
      "id": "ApproachAndAlign",
      "type": "Action",
      "ports": {"target":"pot","tolerance":0.005,"timeout_ms":1000},
      "description": "Fine alignment before grasping pot"
    },
    {
      "id": "LowerUntilContact",
      "type": "Action",
      "ports": {"speed":"slow","max_depth":0.05,"force_threshold":5,"timeout_ms":1000},
      "description": "Descends until gentle contact sensed"
    },
    {
      "id": "CloseGripper",
      "type": "Action",
      "ports": {"force":10,"timeout_ms":800},
      "description": "Closes gripper to grasp the pot"
    },
    {
      "id": "IsGraspStable",
      "type": "Condition",
      "ports": {},
      "description": "Checks grasp stability"
    },
    {
      "id": "IsObjectVisible_sink",
      "type": "Condition",
      "ports": {"target":"sink"},
      "description": "Returns true if sink is visible to perception"
    },
    {
      "id": "DetectObject_sink",
      "type": "Action",
      "ports": {"target":"sink","timeout_ms":800},
      "description": "Detects and localizes the sink"
    },
    {
      "id": "MoveAbove_sink",
      "type": "Action",
      "ports": {"target":"sink","offset_z":0.10,"timeout_ms":1000},
      "description": "Moves gripper above the sink"
    },
    {
      "id": "ApproachAndAlign_sink",
      "type": "Action",
      "ports": {"target":"sink","tolerance":0.005,"timeout_ms":1000},
      "description": "Align for placement over sink"
    },
    {
      "id": "PlaceOnSurface",
      "type": "Action",
      "ports": {"target":"pot","area_id":"sink","yaw_deg":0,"press_force":10,"timeout_ms":1000},
      "description": "Places pot onto sink surface"
    },
    {
      "id": "OpenGripper_place",
      "type": "Action",
      "ports": {"width":0.08,"timeout_ms":500},
      "description": "Opens gripper to release pot"
    },
    {
      "id": "Retreat",
      "type": "Action",
      "ports": {"distance":0.10,"timeout_ms":1000},
      "description": "Moves gripper away from sink area"
    },
    {
      "id": "Wait",
      "type": "Action",
      "ports": {"timeout_ms":500},
      "description": "Waits briefly after retreat"
    }
  ],
  "tree_stats": {"nodes_total": 18, "actions": 13, "conditions": 3, "depth": 2},
  "failure_modes": [
    "Pot or sink not detected",
    "Failed grasp or unstable grasp",
    "Place action fails (obstruction or misalignment)"
  ],
  "recovery_strategy": [
    "Retry scan actions up to allowed attempts",
    "Repeat detection and approach if grasp fails",
    "Fallback to alternative detection if location is not visible"
  ],
  "assumptions": [
    "All frames [0]..[8] show an unchanging static scene; no visible evidence of movement. No visible manipulation of the pot.",
    "BT assumes standard pick and place phases inferred from dataset and instruction, not confirmed by frames.",
    "No robot arm, gripper, or actuation visible in any frame.",
    "Object and scene layout matches the instruction intent."
  ],
  "evaluation_notes": {
    "expected_success_criteria": [
      "Pot fully located within sink area at task completion",
      "No spillage or knocks"
    ],
    "test_scenarios": [
      "happy path",
      "object_missing",
      "grasp_fail",
      "perception_noise"
    ]
  },
  "timing": {"model_reported_tokens": null, "client_elapsed_ms": null},
  "local_annotations": [
    {
      "frame": "frame_0",
      "phase": "perceive",
      "active_leaf": {"id":"IsObjectVisible","attrs":{"target":"pot"}},
      "active_path_ids": []
    },
    {
      "frame": "frame_1",
      "phase": "perceive",
      "active_leaf": {"id":"ScanForTarget","attrs":{"target":"pot","pattern":"raster","max_attempts":3,"timeout_ms":1000}},
      "active_path_ids": []
    },
    {
      "frame": "frame_2",
      "phase": "approach",
      "active_leaf": {"id":"DetectObject","attrs":{"target":"pot","timeout_ms":800}},
      "active_path_ids": []
    },
    {
      "frame": "frame_3",
      "phase": "approach",
      "active_leaf": {"id":"MoveAbove","attrs":{"target":"pot","offset_z":0.05,"timeout_ms":1000}},
      "active_path_ids": []
    },
    {
      "frame": "frame_4",
      "phase": "verify",
      "active_leaf": {"id":"ComputeGraspPose","attrs":{"target":"pot","strategy":"top","result_key":"std_top"}},
      "active_path_ids": []
    },
    {
      "frame": "frame_5",
      "phase": "grasp",
      "active_leaf": {"id":"CloseGripper","attrs":{"force":10,"timeout_ms":800}},
      "active_path_ids": []
    },
    {
      "frame": "frame_6",
      "phase": "transfer",
      "active_leaf": {"id":"MoveAbove_sink","attrs":{"target":"sink","offset_z":0.10,"timeout_ms":1000}},
      "active_path_ids": []
    },
    {
      "frame": "frame_7",
      "phase": "place",
      "active_leaf": {"id":"PlaceOnSurface","attrs":{"target":"pot","area_id":"sink","yaw_deg":0,"press_force":10,"timeout_ms":1000}},
      "active_path_ids": []
    },
    {
      "frame": "frame_8",
      "phase": "retreat",
      "active_leaf": {"id":"Retreat","attrs":{"distance":0.10,"timeout_ms":1000}},
      "active_path_ids": []
    }
  ]
}