{
  "frame_index": 3,
  "local_intent": "Perceive the drawer handle, set yaw to 90, then approach and align precisely to the handle.",
  "plugs_into": { "path_from_root": ["MainTree"], "mode": "replace-only" },
  "bb_read": [],
  "bb_write": [],
  "assumptions": [
    "Line of sight to drawer_handle",
    "No contact required during approach"
  ],
  "coherence_with_global": "Implements the approach phase consistent with the global plan: detect and confirm visibility, orient TCP to 90 deg, perform ApproachAndAlign at tolerance 0.005, and verify orientation.",
  "format_checks": {
    "single_root_composite": true,
    "decorators_single_child": true,
    "only_known_nodes": true,
    "only_binned_values": true
  }
}
