{
  "frame_index": 5,
  "local_intent": "Detect block and target, align and set yaw to 45째, push the T-block 0.2m at 45째, then verify proximity to target marker.",
  "plugs_into": { "path_from_root": ["MainTree"], "mode": "replace-only" },
  "bb_read": [],
  "bb_write": [],
  "assumptions": [],
  "coherence_with_global": "Matches global flow: retry perception for block and marker, approach and align, set yaw to 45째, execute push (0.2 at 45째), and verify with IsAt(target_marker).",
  "format_checks": {
    "single_root_composite": true,
    "decorators_single_child": true,
    "only_known_nodes": true,
    "only_binned_values": true
  }
}