{
  "frame_index": 5,
  "local_intent": "Release the grape onto the plate by opening the gripper after gentle contact above the plate.",
  "plugs_into": { "path_from_root": ["MainTree"], "mode": "replace-only" },
  "bb_read": [],
  "bb_write": [],
  "assumptions": [
    "Grape is currently held in the gripper",
    "Plate pose is known enough to approach from above"
  ],
  "coherence_with_global": "Matches the placement phase of the global plan: approach above plate, lower until contact, then open gripper to release.",
  "format_checks": {
    "single_root_composite": true,
    "decorators_single_child": true,
    "only_known_nodes": true,
    "only_binned_values": true
  }
}
