{
  "frame_index": 3,
  "local_intent": "Perceive the T-block, align to it, set yaw 90 deg, push it 0.1 straight at 90 deg, and verify visibility.",
  "plugs_into": { "path_from_root": ["MainTree"], "mode": "replace-only" },
  "bb_read": [],
  "bb_write": [],
  "assumptions": ["Block remains in view after push", "Safe to approach directly for alignment"],
  "coherence_with_global": "Matches the global plan segment: visibility with retry scan, align to t_block, set yaw=90, perform push with specified parameters, then verify.",
  "format_checks": {
    "single_root_composite": true,
    "decorators_single_child": true,
    "only_known_nodes": true,
    "only_binned_values": true
  }
}