{
  "frame_index": 3,
  "local_intent": "Detect the T-block, approach and align to it within 0.01 m tolerance, then verify continued visibility.",
  "plugs_into": { "path_from_root": ["MainTree"], "mode": "replace-only" },
  "bb_read": [],
  "bb_write": [],
  "assumptions": ["Scene remains static during approach", "Perception provides t_block pose consistently"],
  "coherence_with_global": "Implements the approach phase centered on ApproachAndAlign with identical parameters and preceding perception, consistent with the global plan.",
  "format_checks": {
    "single_root_composite": true,
    "decorators_single_child": true,
    "only_known_nodes": true,
    "only_binned_values": true
  }
}
